tlars-1.0.0.dist-info/WHEEL
tlars-1.0.0.dist-info/RECORD
tlars-1.0.0.dist-info/top_level.txt
tlars-1.0.0.dist-info/METADATA
tlars.libs/libarmadillo-e18ff089.so.12.6.4
tlars/__init__.py
tlars/tlars_cpp.cpython-311-x86_64-linux-gnu.so
