Metadata-Version: 2.2
Name: tlars
Version: 1.0.0
Summary: Python port of the tlars R package for Terminating-LARS (T-LARS) algorithm
Home-page: https://github.com/author/tlars-python
Author: Arnau Vilella
Author-email: Arnau Vilella <avp@connect.ust.hk>
License: MIT
Project-URL: Homepage, https://github.com/ArnauVilella/tlars-python-2
Project-URL: Bug Tracker, https://github.com/ArnauVilella/tlars-python-2/issues
Classifier: Programming Language :: Python :: 3
Classifier: License :: OSI Approved :: MIT License
Classifier: Operating System :: POSIX :: Linux
Classifier: Topic :: Scientific/Engineering :: Mathematics
Classifier: Topic :: Scientific/Engineering :: Artificial Intelligence
Classifier: Intended Audience :: Science/Research
Requires-Python: >=3.6
Requires-Dist: numpy>=1.19.0
Dynamic: author
Dynamic: home-page
Dynamic: requires-python
